cubmods/__init__.py
cubmods/_cubsh2.py
cubmods/_cubsh2_ywxu.py
cubmods/_cushk.py
cubmods/cub.py
cubmods/cub_0w.py
cubmods/cub_y0.py
cubmods/cub_yw.py
cubmods/cube.py
cubmods/cube_0w0.py
cubmods/cube_ywz.py
cubmods/cubsh.py
cubmods/cubsh_ywx.py
cubmods/cush.py
cubmods/cush2.py
cubmods/cush2_x0.py
cubmods/cush2_xx.py
cubmods/cush_x.py
cubmods/gem.py
cubmods/general.py
cubmods/ihg.py
cubmods/ihg_v.py
cubmods/multicub.py
cubmods/smry.py
cubmods/.github/workflows/publish.yml
cubmods-0.0.3.dist-info/METADATA
cubmods-0.0.3.dist-info/WHEEL
cubmods-0.0.3.dist-info/licenses/LICENSE
cubmods-0.0.3.dist-info/RECORD
