Metadata-Version: 2.4
Name: cubmods
Version: 0.0.3
Summary: CUB models for ordinal responses.
Project-URL: Documentation, https://github.com/maxdevblock/cubmods
Project-URL: Issues, https://github.com/maxdevblock/cubmods/issues
Project-URL: Source, https://github.com/maxdevblock/cubmods
Author-email: Massimo Pierini <cub@maxpierini.it>
License-Expression: MIT
License-File: LICENSE
Keywords: CUB,ordinal responses,statistics
Classifier: Development Status :: 4 - Beta
Classifier: Programming Language :: Python
Classifier: Programming Language :: Python :: 3.8
Classifier: Programming Language :: Python :: 3.9
Classifier: Programming Language :: Python :: 3.10
Classifier: Programming Language :: Python :: 3.11
Classifier: Programming Language :: Python :: 3.12
Requires-Python: >=3.8
Requires-Dist: matplotlib
Requires-Dist: numpy
Requires-Dist: pandas
Requires-Dist: scipy
Requires-Dist: statsmodels
